LICENSE
MANIFEST.in
README
TODO
ez_setup.py
setup.py
dap/__init__.py
dap/client.py
dap/dtypes.py
dap/exceptions.py
dap/helper.py
dap/lib.py
dap/proxy.py
dap/server.py
dap/xdr.py
dap.egg-info/PKG-INFO
dap.egg-info/SOURCES.txt
dap.egg-info/dependency_links.txt
dap.egg-info/entry_points.txt
dap.egg-info/namespace_packages.txt
dap.egg-info/not-zip-safe
dap.egg-info/requires.txt
dap.egg-info/top_level.txt
dap/parsers/__init__.py
dap/parsers/das.py
dap/parsers/dds.py
dap/plugins/__init__.py
dap/plugins/csvfiles.py
dap/plugins/lib.py
dap/plugins/templates.py
dap/plugins/paster_templates/setup.cfg
dap/plugins/paster_templates/setup.py_tmpl
dap/plugins/paster_templates/dap/__init__.py
dap/plugins/paster_templates/dap/plugins/__init__.py
dap/plugins/paster_templates/dap/plugins/+package+/__init__.py
dap/responses/__init__.py
dap/responses/ascii.py
dap/responses/das.py
dap/responses/dds.py
dap/responses/dods.py
dap/responses/help.py
dap/responses/version.py
dap/util/__init__.py
dap/util/filter.py
dap/util/http.py
dap/util/ordereddict.py
dap/util/safeeval.py
dap/util/socks.py
dap/util/wsgi_intercept.py
dap/wsgi/__init__.py
dap/wsgi/application.py
dap/wsgi/proxy.py
dap/wsgi/templates.py
dap/wsgi/paster_templates/server.ini_tmpl
dap/wsgi/paster_templates/+package+.egg-info/not-zip-safe
dap/wsgi/paster_templates/data/sample.csv
dap/wsgi/paster_templates/template/index.tmpl
docs/Changelog
docs/bugs
docs/copying
docs/history
tests/test0.py
tests/test1.py
tests/test2.py
tests/test3.py
tests/test4.py