Metadata-Version: 1.0
Name: dap
Version: 2.2.6.7
Summary: DAP (Data Access Protocol) client and server for Python.
Home-page: http://pydap.org/
Author: Roberto De Almeida
Author-email: rob@pydap.org
License: MIT
Keywords: dap opendap dods data science climate meteorology oceanography
Platform: UNKNOWN
Classifier: Development Status :: 4 - Beta
Classifier: Environment :: Console
Classifier: Intended Audience :: Developers
Classifier: Intended Audience :: Science/Research
Classifier: License :: OSI Approved :: MIT License
Classifier: Operating System :: OS Independent
Classifier: Programming Language :: Python
Classifier: Topic :: Internet
Classifier: Topic :: Scientific/Engineering
Classifier: Topic :: Software Development :: Libraries :: Python Modules
